{
  "type": "statement",
  "name": "mBotSetRGBLedAdvanced",
  "connectors": [
    {
      "type": "connector--top",
      "accept": "connector--bottom"
    },
    {
      "type": "connector--bottom",
      "accept": "connector--top"
    },
    {
      "type": "connector--input",
      "accept": "connector--output",
      "acceptType": [
        "all"
      ],
      "suggestedBloqs": [
        "number",
        "selectVariable"
      ],
      "name": "71bf5332-2c85-48af-b203-8f7330a103c9"
    },
    {
      "type": "connector--input",
      "accept": "connector--output",
      "acceptType": [
        "all"
      ],
      "suggestedBloqs": [
        "number",
        "selectVariable"
      ],
      "name": "f7bd7be1-83db-4659-bc15-74644c961ffd"
    },
    {
      "type": "connector--input",
      "accept": "connector--output",
      "acceptType": [
        "all"
      ],
      "suggestedBloqs": [
        "number",
        "selectVariable"
      ],
      "name": "fd291437-2480-49c5-948b-005466065d5a"
    }
  ],
  "bloqClass": "bloq-mbot-setrgbLed",
  "content": [
    [
      {
        "alias": "text",
        "value": "bloq-led-turnon"
      },
      {
        "id": "LED",
        "alias": "dynamicDropdown",
        "options": "mkb_integrated_RGB"
      },
      {
        "alias": "text",
        "value": "bloq-rgbLed-red"
      },
      {
        "bloqInputId": "RED",
        "alias": "bloqInput",
        "acceptType": [
          "all"
        ],
        "suggestedBloqs": [
          "number",
          "selectVariable"
        ],
        "name": "71bf5332-2c85-48af-b203-8f7330a103c9"
      },
      {
        "alias": "text",
        "value": "bloq-rgbLed-green"
      },
      {
        "bloqInputId": "GREEN",
        "alias": "bloqInput",
        "acceptType": [
          "all"
        ],
        "suggestedBloqs": [
          "number",
          "selectVariable"
        ],
        "name": "f7bd7be1-83db-4659-bc15-74644c961ffd"
      },
      {
        "alias": "text",
        "value": "bloq-rgbLed-blue"
      },
      {
        "bloqInputId": "BLUE",
        "alias": "bloqInput",
        "acceptType": [
          "all"
        ],
        "suggestedBloqs": [
          "number",
          "selectVariable"
        ],
        "name": "fd291437-2480-49c5-948b-005466065d5a"
      }
    ]
  ],
  "code": "",
  "arduino": {
    "code": "robot.setLed(º[{LED}.pin.s],{RED}, {GREEN}, {BLUE});"
  },
  "python": {
    "codeLines": [
      {
        "code": "Bloque \"mBotSetRGBLedAdvanced\" no preparado para generar código python"
      }
    ]
  }
}