{
  "type": "statement",
  "name": "mBotSetRGBLedAdvancedFull",
  "connectors": [
    {
      "type": "connector--top",
      "accept": "connector--bottom"
    },
    {
      "type": "connector--bottom",
      "accept": "connector--top"
    },
    {
      "type": "connector--input",
      "accept": "connector--output",
      "acceptType": [
        "all"
      ],
      "suggestedBloqs": [
        "number",
        "selectVariable"
      ],
      "name": "c851fd7a-8f2b-4614-98fa-9aca92f3305b"
    },
    {
      "type": "connector--input",
      "accept": "connector--output",
      "acceptType": [
        "all"
      ],
      "suggestedBloqs": [
        "number",
        "selectVariable"
      ],
      "name": "cb1e5753-6f29-4333-80a3-e23f072752f3"
    },
    {
      "type": "connector--input",
      "accept": "connector--output",
      "acceptType": [
        "all"
      ],
      "suggestedBloqs": [
        "number",
        "selectVariable"
      ],
      "name": "b8418ffe-bee5-4097-9544-6189f97a2141"
    },
    {
      "type": "connector--input",
      "accept": "connector--output",
      "acceptType": [
        "all"
      ],
      "suggestedBloqs": [
        "number",
        "selectVariable"
      ],
      "name": "bee4f9a2-f1b3-43b4-9585-88ee005bd5a2"
    }
  ],
  "bloqClass": "bloq-mbot-setrgbLed",
  "content": [
    [
      {
        "alias": "text",
        "value": "bloq-rgbLed"
      },
      {
        "bloqInputId": "LED",
        "alias": "bloqInput",
        "acceptType": [
          "all"
        ],
        "suggestedBloqs": [
          "number",
          "selectVariable"
        ],
        "name": "c851fd7a-8f2b-4614-98fa-9aca92f3305b"
      },
      {
        "alias": "text",
        "value": "bloq-rgbLed-red"
      },
      {
        "bloqInputId": "RED",
        "alias": "bloqInput",
        "acceptType": [
          "all"
        ],
        "suggestedBloqs": [
          "number",
          "selectVariable"
        ],
        "name": "cb1e5753-6f29-4333-80a3-e23f072752f3"
      },
      {
        "alias": "text",
        "value": "bloq-rgbLed-green"
      },
      {
        "bloqInputId": "GREEN",
        "alias": "bloqInput",
        "acceptType": [
          "all"
        ],
        "suggestedBloqs": [
          "number",
          "selectVariable"
        ],
        "name": "b8418ffe-bee5-4097-9544-6189f97a2141"
      },
      {
        "alias": "text",
        "value": "bloq-rgbLed-blue"
      },
      {
        "bloqInputId": "BLUE",
        "alias": "bloqInput",
        "acceptType": [
          "all"
        ],
        "suggestedBloqs": [
          "number",
          "selectVariable"
        ],
        "name": "bee4f9a2-f1b3-43b4-9585-88ee005bd5a2"
      }
    ]
  ],
  "code": "",
  "arduino": {
    "code": "robot.setLed({LED},{RED}, {GREEN}, {BLUE});"
  },
  "python": {
    "codeLines": [
      {
        "code": "Bloque \"mBotSetRGBLedAdvancedFull\" no preparado para generar código python"
      }
    ]
  }
}