{
  "type": "statement",
  "name": "mBotBuzzerAdvanced",
  "connectors": [
    {
      "type": "connector--top",
      "accept": "connector--bottom"
    },
    {
      "type": "connector--bottom",
      "accept": "connector--top"
    },
    {
      "type": "connector--input",
      "accept": "connector--output",
      "acceptType": [
        "float"
      ],
      "suggestedBloqs": [
        "number",
        "selectVariable"
      ],
      "name": "72553776-a4a4-4f20-b034-a42e11cc6993"
    },
    {
      "type": "connector--input",
      "accept": "connector--output",
      "acceptType": [
        "float"
      ],
      "suggestedBloqs": [
        "number",
        "selectVariable"
      ],
      "name": "4c046272-2e8a-4093-9957-e3a4ab8ae6b8"
    }
  ],
  "bloqClass": "bloq-mbot-buzzer",
  "content": [
    [
      {
        "alias": "text",
        "value": "bloq-mbot-buzzer-advanced-play"
      },
      {
        "bloqInputId": "NOTE",
        "alias": "bloqInput",
        "acceptType": [
          "float"
        ],
        "suggestedBloqs": [
          "number",
          "selectVariable"
        ],
        "name": "72553776-a4a4-4f20-b034-a42e11cc6993"
      },
      {
        "alias": "text",
        "value": "bloq-mbot-buzzer-advanced-for"
      },
      {
        "bloqInputId": "SECONDS",
        "alias": "bloqInput",
        "acceptType": [
          "float"
        ],
        "suggestedBloqs": [
          "number",
          "selectVariable"
        ],
        "name": "4c046272-2e8a-4093-9957-e3a4ab8ae6b8"
      },
      {
        "alias": "text",
        "value": "bloq-mbot-buzzer-advanced-ms"
      }
    ]
  ],
  "code": "",
  "arduino": {
    "needInstanceOf": [
      {
        "name": "mBotBuzzerPin",
        "type": "const int",
        "equals": "8"
      }
    ],
    "code": "tone(mBotBuzzerPin,{NOTE},{SECONDS});\ndelay({SECONDS});"
  },
  "python": {
    "codeLines": [
      {
        "code": "Bloque \"mBotBuzzerAdvanced\" no preparado para generar código python"
      }
    ]
  }
}