{
  "type": "output",
  "name": "substringAdvanced",
  "connectors": [
    {
      "type": "connector--output",
      "accept": "connector--input"
    },
    {
      "type": "connector--input",
      "accept": "connector--output",
      "acceptType": [
        "all"
      ],
      "suggestedBloqs": [
        "selectVariable"
      ],
      "name": "0da1a16e-f259-4a96-907d-7839956ade0b"
    },
    {
      "type": "connector--input",
      "accept": "connector--output",
      "acceptType": [
        "all"
      ],
      "suggestedBloqs": [
        "number",
        "selectVariable"
      ],
      "name": "062a89a7-882b-4756-8b3d-3b325a4c6dd1"
    },
    {
      "type": "connector--input",
      "accept": "connector--output",
      "acceptType": [
        "all"
      ],
      "suggestedBloqs": [
        "number",
        "selectVariable"
      ],
      "name": "c5e40f56-1dc9-4bfc-8c6e-766fc55cfbe5"
    }
  ],
  "bloqClass": "bloq-string",
  "content": [
    [
      {
        "alias": "text",
        "value": "Extraer texto de"
      },
      {
        "bloqInputId": "STRING",
        "alias": "bloqInput",
        "acceptType": [
          "all"
        ],
        "suggestedBloqs": [
          "selectVariable"
        ],
        "name": "0da1a16e-f259-4a96-907d-7839956ade0b"
      },
      {
        "alias": "text",
        "value": "empezando en la posición"
      },
      {
        "bloqInputId": "FROM",
        "alias": "bloqInput",
        "acceptType": [
          "all"
        ],
        "suggestedBloqs": [
          "number",
          "selectVariable"
        ],
        "name": "062a89a7-882b-4756-8b3d-3b325a4c6dd1"
      },
      {
        "alias": "text",
        "value": "y acabando en la posición"
      },
      {
        "bloqInputId": "TO",
        "alias": "bloqInput",
        "acceptType": [
          "all"
        ],
        "suggestedBloqs": [
          "number",
          "selectVariable"
        ],
        "name": "c5e40f56-1dc9-4bfc-8c6e-766fc55cfbe5"
      }
    ]
  ],
  "returnType": {
    "type": "simple",
    "value": "String"
  },
  "arduino": {
    "code": "{STRING}.substring({FROM}, {TO})"
  },
  "python": {
    "codeLines": [
      {
        "code": "Bloque \"substringAdvanced\" no preparado para generar código python"
      }
    ]
  }
}