{
  "type": "output",
  "name": "substringAdvanced",
  "connectors": [
    {
      "type": "connector--output",
      "accept": "connector--input"
    },
    {
      "type": "connector--input",
      "accept": "connector--output",
      "acceptType": [
        "all"
      ],
      "suggestedBloqs": [
        "selectVariable"
      ],
      "name": "8709dd0d-c621-4491-b60c-321520a9fbd9"
    },
    {
      "type": "connector--input",
      "accept": "connector--output",
      "acceptType": [
        "all"
      ],
      "suggestedBloqs": [
        "number",
        "selectVariable"
      ],
      "name": "cc9d06ca-624e-4179-ba12-db1b9016780a"
    },
    {
      "type": "connector--input",
      "accept": "connector--output",
      "acceptType": [
        "all"
      ],
      "suggestedBloqs": [
        "number",
        "selectVariable"
      ],
      "name": "0e2dfdc1-7124-43c4-b71d-66a715302667"
    }
  ],
  "bloqClass": "bloq-string",
  "content": [
    [
      {
        "alias": "text",
        "value": "Extraer texto de"
      },
      {
        "bloqInputId": "STRING",
        "alias": "bloqInput",
        "acceptType": [
          "all"
        ],
        "suggestedBloqs": [
          "selectVariable"
        ],
        "name": "8709dd0d-c621-4491-b60c-321520a9fbd9"
      },
      {
        "alias": "text",
        "value": "empezando en la posición"
      },
      {
        "bloqInputId": "FROM",
        "alias": "bloqInput",
        "acceptType": [
          "all"
        ],
        "suggestedBloqs": [
          "number",
          "selectVariable"
        ],
        "name": "cc9d06ca-624e-4179-ba12-db1b9016780a"
      },
      {
        "alias": "text",
        "value": "y acabando en la posición"
      },
      {
        "bloqInputId": "TO",
        "alias": "bloqInput",
        "acceptType": [
          "all"
        ],
        "suggestedBloqs": [
          "number",
          "selectVariable"
        ],
        "name": "0e2dfdc1-7124-43c4-b71d-66a715302667"
      }
    ]
  ],
  "returnType": {
    "type": "simple",
    "value": "String"
  },
  "arduino": {
    "code": "{STRING}.substring({FROM}, {TO})"
  },
  "python": {
    "codeLines": [
      {
        "code": "Bloque \"substringAdvanced\" no preparado para generar código python"
      }
    ]
  }
}