{
  "type": "statement",
  "name": "mkbSetExternalRGBLedAdvancedFull",
  "connectors": [
    {
      "type": "connector--top",
      "accept": "connector--bottom"
    },
    {
      "type": "connector--bottom",
      "accept": "connector--top"
    },
    {
      "type": "connector--input",
      "accept": "connector--output",
      "acceptType": [
        "all"
      ],
      "suggestedBloqs": [
        "number",
        "selectVariable"
      ],
      "name": "b6a27c2e-6526-4eca-b4bc-6f151ede8864"
    },
    {
      "type": "connector--input",
      "accept": "connector--output",
      "acceptType": [
        "all"
      ],
      "suggestedBloqs": [
        "number",
        "selectVariable"
      ],
      "name": "7faaaf3d-e448-4e1c-b6fb-a7bb5a5e9453"
    },
    {
      "type": "connector--input",
      "accept": "connector--output",
      "acceptType": [
        "all"
      ],
      "suggestedBloqs": [
        "number",
        "selectVariable"
      ],
      "name": "2a9400bb-d517-4c4f-973a-a2ef30c31d5c"
    },
    {
      "type": "connector--input",
      "accept": "connector--output",
      "acceptType": [
        "all"
      ],
      "suggestedBloqs": [
        "number",
        "selectVariable"
      ],
      "name": "ae1cd031-68be-4959-b358-2993663f4a8c"
    }
  ],
  "bloqClass": "bloq-mbot-setrgbLed",
  "content": [
    [
      {
        "alias": "text",
        "value": "bloq-rgbLed"
      },
      {
        "bloqInputId": "LED",
        "alias": "bloqInput",
        "acceptType": [
          "all"
        ],
        "suggestedBloqs": [
          "number",
          "selectVariable"
        ],
        "name": "b6a27c2e-6526-4eca-b4bc-6f151ede8864"
      },
      {
        "alias": "text",
        "value": "bloq-rgbLed-red"
      },
      {
        "bloqInputId": "RED",
        "alias": "bloqInput",
        "acceptType": [
          "all"
        ],
        "suggestedBloqs": [
          "number",
          "selectVariable"
        ],
        "name": "7faaaf3d-e448-4e1c-b6fb-a7bb5a5e9453"
      },
      {
        "alias": "text",
        "value": "bloq-rgbLed-green"
      },
      {
        "bloqInputId": "GREEN",
        "alias": "bloqInput",
        "acceptType": [
          "all"
        ],
        "suggestedBloqs": [
          "number",
          "selectVariable"
        ],
        "name": "2a9400bb-d517-4c4f-973a-a2ef30c31d5c"
      },
      {
        "alias": "text",
        "value": "bloq-rgbLed-blue"
      },
      {
        "bloqInputId": "BLUE",
        "alias": "bloqInput",
        "acceptType": [
          "all"
        ],
        "suggestedBloqs": [
          "number",
          "selectVariable"
        ],
        "name": "ae1cd031-68be-4959-b358-2993663f4a8c"
      },
      {
        "alias": "text",
        "value": "in"
      },
      {
        "id": "RGBLED",
        "alias": "dynamicDropdown",
        "options": "mkb_RGBLed"
      }
    ]
  ],
  "code": "",
  "arduino": {
    "code": "{RGBLED}.showColor({LED},{RED}, {GREEN}, {BLUE});"
  },
  "python": {
    "codeLines": [
      {
        "code": "Bloque \"mkbSetExternalRGBLedAdvancedFull\" no preparado para generar código python"
      }
    ]
  }
}