{
  "type": "statement-input",
  "name": "ifAdvanced",
  "connectors": [
    {
      "type": "connector--top",
      "accept": "connector--bottom"
    },
    {
      "type": "connector--bottom",
      "accept": "connector--top"
    },
    {
      "type": "connector--root",
      "accept": "connector--top"
    },
    {
      "type": "connector--input",
      "accept": "connector--output",
      "acceptType": "all",
      "name": "a7de6d11-2bf9-4c83-a10c-f247b4e59ab7"
    }
  ],
  "bloqClass": "bloq-if",
  "content": [
    [
      {
        "alias": "text",
        "value": "bloq-if-if"
      },
      {
        "bloqInputId": "CONDITION",
        "alias": "bloqInput",
        "acceptType": "all",
        "name": "a7de6d11-2bf9-4c83-a10c-f247b4e59ab7"
      },
      {
        "alias": "text",
        "value": "bloq-if-exec"
      }
    ]
  ],
  "code": "if({CONDITION}){{STATEMENTS}}"
}