{
  "type": "statement",
  "name": "buzzerWithoutPauseAdvanced",
  "connectors": [
    {
      "type": "connector--top",
      "accept": "connector--bottom"
    },
    {
      "type": "connector--bottom",
      "accept": "connector--top"
    },
    {
      "type": "connector--input",
      "accept": "connector--output",
      "acceptType": [
        "all"
      ],
      "suggestedBloqs": [
        "number",
        "selectVariable"
      ],
      "name": "75941a22-46ad-4775-9727-dd8b49edb30b"
    },
    {
      "type": "connector--input",
      "accept": "connector--output",
      "acceptType": [
        "all"
      ],
      "suggestedBloqs": [
        "number",
        "selectVariable"
      ],
      "name": "933e55a4-048b-4c01-b33e-a378fc7b0a91"
    }
  ],
  "bloqClass": "bloq-buzzer-advance",
  "content": [
    [
      {
        "alias": "text",
        "value": "bloq-buzzer-advance-sound"
      },
      {
        "id": "BUZZER",
        "alias": "dynamicDropdown",
        "options": "buzzers"
      },
      {
        "alias": "text",
        "value": "bloq-buzzer-advance-note"
      },
      {
        "bloqInputId": "NOTE",
        "alias": "bloqInput",
        "acceptType": [
          "all"
        ],
        "suggestedBloqs": [
          "number",
          "selectVariable"
        ],
        "name": "75941a22-46ad-4775-9727-dd8b49edb30b"
      },
      {
        "alias": "text",
        "value": "bloq-buzzer-advance-for"
      },
      {
        "bloqInputId": "SECONDS",
        "alias": "bloqInput",
        "acceptType": [
          "all"
        ],
        "suggestedBloqs": [
          "number",
          "selectVariable"
        ],
        "name": "933e55a4-048b-4c01-b33e-a378fc7b0a91"
      },
      {
        "alias": "text",
        "value": "bloq-buzzer-advance-ms"
      },
      {
        "alias": "text",
        "value": "bloq-buzzer-without-pause"
      }
    ]
  ],
  "code": "tone({BUZZER},{NOTE},{SECONDS});",
  "arduino": {
    "code": "tone({BUZZER},{NOTE},{SECONDS});"
  },
  "python": {
    "codeLines": [
      {
        "code": "Bloque \"buzzerWithoutPauseAdvanced\" no preparado para generar código python"
      }
    ]
  }
}