{
  "type": "statement",
  "name": "servoNormalAdvanced",
  "connectors": [
    {
      "type": "connector--top",
      "accept": "connector--bottom"
    },
    {
      "type": "connector--bottom",
      "accept": "connector--top"
    },
    {
      "type": "connector--input",
      "accept": "connector--output",
      "acceptType": "all",
      "name": "2eb8f120-22bb-45fe-8f80-9c76cd68f4d6"
    },
    {
      "type": "connector--input",
      "accept": "connector--output",
      "acceptType": "all",
      "name": "91064ea9-fd7d-42c8-bcdd-854299b0b566"
    }
  ],
  "bloqClass": "bloq-servo-advanced",
  "content": [
    [
      {
        "alias": "text",
        "value": "bloq-servo-advanced-move"
      },
      {
        "bloqInputId": "SERVO",
        "alias": "bloqInput",
        "acceptType": "all",
        "name": "2eb8f120-22bb-45fe-8f80-9c76cd68f4d6"
      },
      {
        "alias": "text",
        "value": "bloq-servo-advanced-to"
      },
      {
        "bloqInputId": "POSITION",
        "alias": "bloqInput",
        "acceptType": "all",
        "name": "91064ea9-fd7d-42c8-bcdd-854299b0b566"
      },
      {
        "alias": "text",
        "value": "bloq-servo-advanced-degrees"
      }
    ]
  ],
  "code": "{SERVO}.write({POSITION});"
}