{
  "type": "output",
  "name": "map",
  "connectors": [
    {
      "type": "connector--output",
      "accept": "connector--input"
    },
    {
      "type": "connector--input",
      "accept": "connector--output",
      "acceptType": "float",
      "name": "b736b7bd-6300-4f41-b53d-a9784b9cf529"
    },
    {
      "type": "connector--input",
      "accept": "connector--output",
      "acceptType": "float",
      "name": "90ec5fbf-3f00-4a13-9f54-55294bba9c35"
    }
  ],
  "bloqClass": "bloq-map",
  "content": [
    [
      {
        "alias": "text",
        "value": "bloq-map-map"
      },
      {
        "bloqInputId": "VAR",
        "alias": "bloqInput",
        "acceptType": "float",
        "name": "b736b7bd-6300-4f41-b53d-a9784b9cf529"
      },
      {
        "alias": "text",
        "value": "bloq-map-value"
      },
      {
        "bloqInputId": "MAXVAL",
        "alias": "bloqInput",
        "acceptType": "float",
        "name": "90ec5fbf-3f00-4a13-9f54-55294bba9c35"
      },
      {
        "alias": "text",
        "value": "]"
      }
    ]
  ],
  "code": "map({VAR},0,1023,0,{MAXVAL})",
  "returnType": {
    "type": "simple",
    "value": "float"
  }
}