{
  "type": "output",
  "name": "random",
  "connectors": [
    {
      "type": "connector--output",
      "accept": "connector--input"
    },
    {
      "type": "connector--input",
      "accept": "connector--output",
      "acceptType": [
        "float"
      ],
      "suggestedBloqs": [
        "number",
        "selectVariable"
      ],
      "name": "f724642c-10cb-49a0-b619-21dc313f488e"
    },
    {
      "type": "connector--input",
      "accept": "connector--output",
      "acceptType": [
        "float"
      ],
      "suggestedBloqs": [
        "number",
        "selectVariable"
      ],
      "name": "a78ef085-7676-44fc-ad20-5882f671a9b2"
    }
  ],
  "bloqClass": "bloq-random",
  "content": [
    [
      {
        "alias": "text",
        "value": "bloq-random-random"
      },
      {
        "bloqInputId": "ARG1",
        "alias": "bloqInput",
        "acceptType": [
          "float"
        ],
        "suggestedBloqs": [
          "number",
          "selectVariable"
        ],
        "name": "f724642c-10cb-49a0-b619-21dc313f488e"
      },
      {
        "alias": "text",
        "value": "bloq-random-and"
      },
      {
        "bloqInputId": "ARG2",
        "alias": "bloqInput",
        "acceptType": [
          "float"
        ],
        "suggestedBloqs": [
          "number",
          "selectVariable"
        ],
        "name": "a78ef085-7676-44fc-ad20-5882f671a9b2"
      }
    ]
  ],
  "code": "random({ARG1},{ARG2}+1)",
  "returnType": {
    "type": "simple",
    "value": "float"
  },
  "arduino": {
    "code": "random({ARG1},{ARG2}+1)"
  },
  "python": {
    "codeLines": [
      {
        "code": "Bloque \"random\" no preparado para generar código python"
      }
    ]
  }
}