{
  "type": "statement",
  "name": "zumjuniorTurnOnLedRGBAdvanced",
  "connectors": [
    {
      "type": "connector--top",
      "accept": "connector--bottom"
    },
    {
      "type": "connector--bottom",
      "accept": "connector--top"
    },
    {
      "type": "connector--input",
      "accept": "connector--output",
      "acceptType": [
        "all"
      ],
      "suggestedBloqs": [
        "number",
        "selectVariable"
      ],
      "name": "9d9bf9f5-744e-417d-a01f-bc8e65788a86"
    },
    {
      "type": "connector--input",
      "accept": "connector--output",
      "acceptType": [
        "all"
      ],
      "suggestedBloqs": [
        "number",
        "selectVariable"
      ],
      "name": "dd2cac10-f873-4765-b0c9-b68234f255ee"
    },
    {
      "type": "connector--input",
      "accept": "connector--output",
      "acceptType": [
        "all"
      ],
      "suggestedBloqs": [
        "number",
        "selectVariable"
      ],
      "name": "01df560e-f979-4ad2-97ea-e3d8cfa097cd"
    }
  ],
  "bloqClass": "bloq-zumjunior-turnon-led-rgb",
  "content": [
    [
      {
        "alias": "text",
        "value": "bloq-zumjunior-turnon-led-rgb"
      },
      {
        "bloqInputId": "RVALUE",
        "alias": "bloqInput",
        "acceptType": [
          "all"
        ],
        "suggestedBloqs": [
          "number",
          "selectVariable"
        ],
        "name": "9d9bf9f5-744e-417d-a01f-bc8e65788a86"
      },
      {
        "bloqInputId": "GVALUE",
        "alias": "bloqInput",
        "acceptType": [
          "all"
        ],
        "suggestedBloqs": [
          "number",
          "selectVariable"
        ],
        "name": "dd2cac10-f873-4765-b0c9-b68234f255ee"
      },
      {
        "bloqInputId": "BVALUE",
        "alias": "bloqInput",
        "acceptType": [
          "all"
        ],
        "suggestedBloqs": [
          "number",
          "selectVariable"
        ],
        "name": "01df560e-f979-4ad2-97ea-e3d8cfa097cd"
      }
    ]
  ],
  "code": "zumJunior.setRGBLED({RVALUE},{GVALUE},{BVALUE});",
  "arduino": {
    "code": "zumJunior.setRGBLED({RVALUE},{GVALUE},{BVALUE});"
  },
  "python": {
    "codeLines": [
      {
        "code": "Bloque \"zumjuniorTurnOnLedRGBAdvanced\" no preparado para generar código python"
      }
    ]
  }
}