{
  "type": "statement",
  "name": "zumjuniorTurnOnLedRGBAdvanced",
  "connectors": [
    {
      "type": "connector--top",
      "accept": "connector--bottom"
    },
    {
      "type": "connector--bottom",
      "accept": "connector--top"
    },
    {
      "type": "connector--input",
      "accept": "connector--output",
      "acceptType": [
        "all"
      ],
      "suggestedBloqs": [
        "number",
        "selectVariable"
      ],
      "name": "580ff5f6-a6a5-4b7c-9219-ec344f0d6e19"
    },
    {
      "type": "connector--input",
      "accept": "connector--output",
      "acceptType": [
        "all"
      ],
      "suggestedBloqs": [
        "number",
        "selectVariable"
      ],
      "name": "ec4a947f-e98f-4ab0-ab0b-fa7f46e65a59"
    },
    {
      "type": "connector--input",
      "accept": "connector--output",
      "acceptType": [
        "all"
      ],
      "suggestedBloqs": [
        "number",
        "selectVariable"
      ],
      "name": "02190616-8562-4140-9d89-6757e91d9f55"
    }
  ],
  "bloqClass": "bloq-zumjunior-turnon-led-rgb",
  "content": [
    [
      {
        "alias": "text",
        "value": "bloq-zumjunior-turnon-led-rgb"
      },
      {
        "bloqInputId": "RVALUE",
        "alias": "bloqInput",
        "acceptType": [
          "all"
        ],
        "suggestedBloqs": [
          "number",
          "selectVariable"
        ],
        "name": "580ff5f6-a6a5-4b7c-9219-ec344f0d6e19"
      },
      {
        "bloqInputId": "GVALUE",
        "alias": "bloqInput",
        "acceptType": [
          "all"
        ],
        "suggestedBloqs": [
          "number",
          "selectVariable"
        ],
        "name": "ec4a947f-e98f-4ab0-ab0b-fa7f46e65a59"
      },
      {
        "bloqInputId": "BVALUE",
        "alias": "bloqInput",
        "acceptType": [
          "all"
        ],
        "suggestedBloqs": [
          "number",
          "selectVariable"
        ],
        "name": "02190616-8562-4140-9d89-6757e91d9f55"
      }
    ]
  ],
  "code": "zumJunior.setRGBLED({RVALUE},{GVALUE},{BVALUE});",
  "arduino": {
    "code": "zumJunior.setRGBLED({RVALUE},{GVALUE},{BVALUE});"
  },
  "python": {
    "codeLines": [
      {
        "code": "Bloque \"zumjuniorTurnOnLedRGBAdvanced\" no preparado para generar código python"
      }
    ]
  }
}