{
  "type": "statement",
  "name": "zumjuniorDisplayCharsAdvanced",
  "connectors": [
    {
      "type": "connector--top",
      "accept": "connector--bottom"
    },
    {
      "type": "connector--bottom",
      "accept": "connector--top"
    },
    {
      "type": "connector--input",
      "accept": "connector--output",
      "acceptType": [
        "all"
      ],
      "suggestedBloqs": [
        "string",
        "selectVariable"
      ],
      "name": "caa7df17-ffbd-435f-b622-0dd2a0fff403"
    }
  ],
  "bloqClass": "bloq-zumjunior-display-number",
  "content": [
    [
      {
        "alias": "text",
        "value": "bloq-zumjunior-display-chars"
      },
      {
        "bloqInputId": "VALUE",
        "alias": "bloqInput",
        "acceptType": [
          "all"
        ],
        "suggestedBloqs": [
          "string",
          "selectVariable"
        ],
        "name": "caa7df17-ffbd-435f-b622-0dd2a0fff403"
      }
    ]
  ],
  "code": "segmentDisplay.displayString({VALUE});",
  "arduino": {
    "code": "segmentDisplay.displayString({VALUE});"
  },
  "python": {
    "codeLines": [
      {
        "code": "Bloque \"zumjuniorDisplayCharsAdvanced\" no preparado para generar código python"
      }
    ]
  }
}