{
  "type": "statement",
  "name": "setArrayVariableAdvanced",
  "connectors": [
    {
      "type": "connector--top",
      "accept": "connector--bottom"
    },
    {
      "type": "connector--bottom",
      "accept": "connector--top"
    },
    {
      "type": "connector--input",
      "accept": "connector--output",
      "acceptType": [
        "all"
      ],
      "suggestedBloqs": [
        "number",
        "string",
        "selectVariable"
      ],
      "name": "79fedd71-f1f1-4f3c-ace3-6b7cd238c58e"
    },
    {
      "type": "connector--input",
      "accept": "connector--output",
      "acceptType": [
        "all"
      ],
      "suggestedBloqs": [
        "number",
        "string",
        "selectVariable"
      ],
      "name": "01f8c2a3-5bf4-4eee-b2b3-ba7ff534a794"
    }
  ],
  "bloqClass": "bloq-set-variableArray",
  "content": [
    [
      {
        "alias": "text",
        "value": "bloq-set-variableArray-variable"
      },
      {
        "id": "NAME",
        "alias": "dynamicDropdown",
        "options": "softwareVars"
      },
      {
        "alias": "text",
        "value": "["
      },
      {
        "bloqInputId": "ITERATOR",
        "alias": "bloqInput",
        "acceptType": [
          "all"
        ],
        "suggestedBloqs": [
          "number",
          "string",
          "selectVariable"
        ],
        "name": "79fedd71-f1f1-4f3c-ace3-6b7cd238c58e"
      },
      {
        "alias": "text",
        "value": "]"
      },
      {
        "alias": "text",
        "value": "="
      },
      {
        "bloqInputId": "VALUE",
        "alias": "bloqInput",
        "acceptType": [
          "all"
        ],
        "suggestedBloqs": [
          "number",
          "string",
          "selectVariable"
        ],
        "name": "01f8c2a3-5bf4-4eee-b2b3-ba7ff534a794"
      }
    ]
  ],
  "code": "{NAME}[{ITERATOR}] = {VALUE};",
  "arduino": {
    "code": "{NAME}[{ITERATOR}] = {VALUE};"
  },
  "python": {
    "codeLines": [
      {
        "code": "Bloque \"setArrayVariableAdvanced\" no preparado para generar código python"
      }
    ]
  }
}