{
  "type": "output",
  "name": "mapAdvanced",
  "connectors": [
    {
      "type": "connector--output",
      "accept": "connector--input"
    },
    {
      "type": "connector--input",
      "accept": "connector--output",
      "acceptType": [
        "float"
      ],
      "suggestedBloqs": [
        "readSensor",
        "selectVariable"
      ],
      "name": "f6762926-93e8-4dcd-8a91-b17c543611ca"
    },
    {
      "type": "connector--input",
      "accept": "connector--output",
      "acceptType": [
        "float"
      ],
      "suggestedBloqs": [
        "number",
        "selectVariable"
      ],
      "name": "6d39bc8c-f760-4ea9-806c-30d65c00d7d7"
    },
    {
      "type": "connector--input",
      "accept": "connector--output",
      "acceptType": [
        "float"
      ],
      "suggestedBloqs": [
        "number",
        "selectVariable"
      ],
      "name": "acca77f4-9663-48d9-a585-5e63a425970e"
    },
    {
      "type": "connector--input",
      "accept": "connector--output",
      "acceptType": [
        "float"
      ],
      "suggestedBloqs": [
        "number",
        "selectVariable"
      ],
      "name": "0ba8a70e-4d86-49ff-ae3b-5ecd515c5e5a"
    },
    {
      "type": "connector--input",
      "accept": "connector--output",
      "acceptType": [
        "float"
      ],
      "suggestedBloqs": [
        "number",
        "selectVariable"
      ],
      "name": "f2f325c1-e533-4260-b324-341b5d53f7d4"
    }
  ],
  "bloqClass": "bloq-map-advanced",
  "content": [
    [
      {
        "alias": "text",
        "value": "bloq-map-advanced-map"
      },
      {
        "bloqInputId": "VAR",
        "alias": "bloqInput",
        "acceptType": [
          "float"
        ],
        "suggestedBloqs": [
          "readSensor",
          "selectVariable"
        ],
        "name": "f6762926-93e8-4dcd-8a91-b17c543611ca"
      },
      {
        "alias": "text",
        "value": "bloq-map-advanced-value"
      },
      {
        "bloqInputId": "INITMIN",
        "alias": "bloqInput",
        "acceptType": [
          "float"
        ],
        "suggestedBloqs": [
          "number",
          "selectVariable"
        ],
        "name": "6d39bc8c-f760-4ea9-806c-30d65c00d7d7"
      },
      {
        "alias": "text",
        "value": "-"
      },
      {
        "bloqInputId": "INITMAX",
        "alias": "bloqInput",
        "acceptType": [
          "float"
        ],
        "suggestedBloqs": [
          "number",
          "selectVariable"
        ],
        "name": "acca77f4-9663-48d9-a585-5e63a425970e"
      },
      {
        "alias": "text",
        "value": "bloq-map-advanced-and"
      },
      {
        "bloqInputId": "FINMIN",
        "alias": "bloqInput",
        "acceptType": [
          "float"
        ],
        "suggestedBloqs": [
          "number",
          "selectVariable"
        ],
        "name": "0ba8a70e-4d86-49ff-ae3b-5ecd515c5e5a"
      },
      {
        "alias": "text",
        "value": "-"
      },
      {
        "bloqInputId": "FINMAX",
        "alias": "bloqInput",
        "acceptType": [
          "float"
        ],
        "suggestedBloqs": [
          "number",
          "selectVariable"
        ],
        "name": "f2f325c1-e533-4260-b324-341b5d53f7d4"
      },
      {
        "alias": "text",
        "value": "]"
      }
    ]
  ],
  "code": "map({VAR},{INITMIN},{INITMAX},{FINMIN},{FINMAX})",
  "returnType": {
    "type": "simple",
    "value": "float"
  },
  "arduino": {
    "code": "map({VAR},{INITMIN},{INITMAX},{FINMIN},{FINMAX})"
  },
  "python": {
    "codeLines": [
      {
        "code": "Bloque \"mapAdvanced\" no preparado para generar código python"
      }
    ]
  }
}