{
  "type": "statement",
  "name": "mkbDrawLineAdvanced",
  "connectors": [
    {
      "type": "connector--top",
      "accept": "connector--bottom"
    },
    {
      "type": "connector--bottom",
      "accept": "connector--top"
    },
    {
      "type": "connector--input",
      "accept": "connector--output",
      "acceptType": [
        "all"
      ],
      "suggestedBloqs": [
        "number",
        "selectVariable"
      ],
      "name": "563df74e-f2ee-443e-8bfd-59c31f7b226b"
    },
    {
      "type": "connector--input",
      "accept": "connector--output",
      "acceptType": [
        "all"
      ],
      "suggestedBloqs": [
        "number",
        "selectVariable"
      ],
      "name": "557b62eb-e808-42e2-bb34-57a8f072ea56"
    },
    {
      "type": "connector--input",
      "accept": "connector--output",
      "acceptType": [
        "all"
      ],
      "suggestedBloqs": [
        "number",
        "selectVariable"
      ],
      "name": "b700b4b1-858e-49a2-b8d3-a5358880d1fa"
    },
    {
      "type": "connector--input",
      "accept": "connector--output",
      "acceptType": [
        "all"
      ],
      "suggestedBloqs": [
        "number",
        "selectVariable"
      ],
      "name": "6e3a204a-4ee4-449b-aa4d-fb5eac68c597"
    }
  ],
  "bloqClass": "bloq-mbot-color",
  "content": [
    [
      {
        "alias": "text",
        "value": "Dibujar línea desde x1:"
      },
      {
        "bloqInputId": "COLUMN",
        "alias": "bloqInput",
        "acceptType": [
          "all"
        ],
        "suggestedBloqs": [
          "number",
          "selectVariable"
        ],
        "name": "563df74e-f2ee-443e-8bfd-59c31f7b226b"
      },
      {
        "alias": "text",
        "value": "y1:"
      },
      {
        "bloqInputId": "ROW",
        "alias": "bloqInput",
        "acceptType": [
          "all"
        ],
        "suggestedBloqs": [
          "number",
          "selectVariable"
        ],
        "name": "557b62eb-e808-42e2-bb34-57a8f072ea56"
      },
      {
        "alias": "text",
        "value": "hasta x2:"
      },
      {
        "bloqInputId": "COLUMNF",
        "alias": "bloqInput",
        "acceptType": [
          "all"
        ],
        "suggestedBloqs": [
          "number",
          "selectVariable"
        ],
        "name": "b700b4b1-858e-49a2-b8d3-a5358880d1fa"
      },
      {
        "alias": "text",
        "value": "y2:"
      },
      {
        "bloqInputId": "ROWF",
        "alias": "bloqInput",
        "acceptType": [
          "all"
        ],
        "suggestedBloqs": [
          "number",
          "selectVariable"
        ],
        "name": "6e3a204a-4ee4-449b-aa4d-fb5eac68c597"
      },
      {
        "alias": "text",
        "value": "in-the"
      },
      {
        "id": "LEDMATRIX",
        "alias": "dynamicDropdown",
        "options": "ledMatrix"
      }
    ]
  ],
  "code": "",
  "arduino": {
    "code": "{LEDMATRIX}.drawLine({COLUMN},{ROW},{COLUMNF},{ROWF});"
  },
  "python": {
    "codeLines": [
      {
        "code": "Bloque \"mkbDrawLineAdvanced\" no preparado para generar código python"
      }
    ]
  }
}