{
  "type": "statement",
  "name": "mkbDrawLineAdvanced",
  "connectors": [
    {
      "type": "connector--top",
      "accept": "connector--bottom"
    },
    {
      "type": "connector--bottom",
      "accept": "connector--top"
    },
    {
      "type": "connector--input",
      "accept": "connector--output",
      "acceptType": [
        "all"
      ],
      "suggestedBloqs": [
        "number",
        "selectVariable"
      ],
      "name": "7718fef0-e333-4be7-879c-5d2a43c70f05"
    },
    {
      "type": "connector--input",
      "accept": "connector--output",
      "acceptType": [
        "all"
      ],
      "suggestedBloqs": [
        "number",
        "selectVariable"
      ],
      "name": "2f8e424d-5e0f-4a74-8fd6-5893bc7356b4"
    },
    {
      "type": "connector--input",
      "accept": "connector--output",
      "acceptType": [
        "all"
      ],
      "suggestedBloqs": [
        "number",
        "selectVariable"
      ],
      "name": "c2dda869-7d7e-4376-9425-9ffe3407ad2e"
    },
    {
      "type": "connector--input",
      "accept": "connector--output",
      "acceptType": [
        "all"
      ],
      "suggestedBloqs": [
        "number",
        "selectVariable"
      ],
      "name": "17dd7445-4b14-4e92-9628-06846f1c942e"
    }
  ],
  "bloqClass": "bloq-mbot-color",
  "content": [
    [
      {
        "alias": "text",
        "value": "Dibujar línea desde x1:"
      },
      {
        "bloqInputId": "COLUMN",
        "alias": "bloqInput",
        "acceptType": [
          "all"
        ],
        "suggestedBloqs": [
          "number",
          "selectVariable"
        ],
        "name": "7718fef0-e333-4be7-879c-5d2a43c70f05"
      },
      {
        "alias": "text",
        "value": "y1:"
      },
      {
        "bloqInputId": "ROW",
        "alias": "bloqInput",
        "acceptType": [
          "all"
        ],
        "suggestedBloqs": [
          "number",
          "selectVariable"
        ],
        "name": "2f8e424d-5e0f-4a74-8fd6-5893bc7356b4"
      },
      {
        "alias": "text",
        "value": "hasta x2:"
      },
      {
        "bloqInputId": "COLUMNF",
        "alias": "bloqInput",
        "acceptType": [
          "all"
        ],
        "suggestedBloqs": [
          "number",
          "selectVariable"
        ],
        "name": "c2dda869-7d7e-4376-9425-9ffe3407ad2e"
      },
      {
        "alias": "text",
        "value": "y2:"
      },
      {
        "bloqInputId": "ROWF",
        "alias": "bloqInput",
        "acceptType": [
          "all"
        ],
        "suggestedBloqs": [
          "number",
          "selectVariable"
        ],
        "name": "17dd7445-4b14-4e92-9628-06846f1c942e"
      },
      {
        "alias": "text",
        "value": "in-the"
      },
      {
        "id": "LEDMATRIX",
        "alias": "dynamicDropdown",
        "options": "ledMatrix"
      }
    ]
  ],
  "code": "",
  "arduino": {
    "code": "{LEDMATRIX}.drawLine({COLUMN},{ROW},{COLUMNF},{ROWF});"
  },
  "python": {
    "codeLines": [
      {
        "code": "Bloque \"mkbDrawLineAdvanced\" no preparado para generar código python"
      }
    ]
  }
}