{
  "type": "output",
  "name": "botbloqManipulatorCanMoveAdvanced",
  "connectors": [
    {
      "type": "connector--output",
      "accept": "connector--input"
    },
    {
      "type": "connector--input",
      "accept": "connector--output",
      "acceptType": [
        "all"
      ],
      "suggestedBloqs": [
        "number",
        "selectVariable"
      ],
      "name": "497da0fa-2c83-495a-b01e-c6039981bba1"
    },
    {
      "type": "connector--input",
      "accept": "connector--output",
      "acceptType": [
        "all"
      ],
      "suggestedBloqs": [
        "number",
        "selectVariable"
      ],
      "name": "c827e3a0-8b64-4bec-bd01-5ce2155b564b"
    },
    {
      "type": "connector--input",
      "accept": "connector--output",
      "acceptType": [
        "all"
      ],
      "suggestedBloqs": [
        "number",
        "selectVariable"
      ],
      "name": "7a4b2238-c68c-412b-aea0-d1b85b13bdb6"
    }
  ],
  "bloqClass": "bloq-botbloq-manipulator-canmove",
  "content": [
    [
      {
        "alias": "text",
        "value": "can-move-to"
      },
      {
        "alias": "text",
        "value": "x:"
      },
      {
        "bloqInputId": "X",
        "alias": "bloqInput",
        "acceptType": [
          "all"
        ],
        "suggestedBloqs": [
          "number",
          "selectVariable"
        ],
        "name": "497da0fa-2c83-495a-b01e-c6039981bba1"
      },
      {
        "alias": "text",
        "value": "y:"
      },
      {
        "bloqInputId": "Y",
        "alias": "bloqInput",
        "acceptType": [
          "all"
        ],
        "suggestedBloqs": [
          "number",
          "selectVariable"
        ],
        "name": "c827e3a0-8b64-4bec-bd01-5ce2155b564b"
      },
      {
        "alias": "text",
        "value": "z:"
      },
      {
        "bloqInputId": "Z",
        "alias": "bloqInput",
        "acceptType": [
          "all"
        ],
        "suggestedBloqs": [
          "number",
          "selectVariable"
        ],
        "name": "7a4b2238-c68c-412b-aea0-d1b85b13bdb6"
      },
      {
        "alias": "text",
        "value": "?"
      }
    ]
  ],
  "code": "",
  "returnType": {
    "type": "simple",
    "value": "bool"
  },
  "python": {
    "libraries": [
      "BotbloqManipulator"
    ],
    "needInstanceOf": [
      {
        "name": "manipulator",
        "type": "BotbloqManipulator"
      }
    ],
    "codeLines": [
      {
        "code": "vehicle.canMove({X}, {Y}, {Z})"
      }
    ]
  }
}