{
  "type": "statement",
  "name": "setVariable",
  "connectors": [
    {
      "type": "connector--top",
      "accept": "connector--bottom"
    },
    {
      "type": "connector--bottom",
      "accept": "connector--top"
    },
    {
      "type": "connector--input",
      "accept": "connector--output",
      "acceptType": {
        "type": "fromDynamicDropdown",
        "idDropdown": "NAME",
        "options": "softwareVars"
      },
      "name": "79e38ebc-6e70-4a01-a939-fb0ef84942c9"
    }
  ],
  "bloqClass": "bloq-set-variable",
  "content": [
    [
      {
        "alias": "text",
        "value": "bloq-set-variable-variable"
      },
      {
        "id": "NAME",
        "alias": "dynamicDropdown",
        "options": "softwareVars"
      },
      {
        "alias": "text",
        "value": "="
      },
      {
        "bloqInputId": "VALUE",
        "alias": "bloqInput",
        "acceptType": {
          "type": "fromDynamicDropdown",
          "idDropdown": "NAME",
          "options": "softwareVars"
        },
        "name": "79e38ebc-6e70-4a01-a939-fb0ef84942c9"
      }
    ]
  ],
  "code": "{NAME} = {VALUE};"
}