{
  "type": "statement",
  "name": "buzzerAdvanced",
  "connectors": [
    {
      "type": "connector--top",
      "accept": "connector--bottom"
    },
    {
      "type": "connector--bottom",
      "accept": "connector--top"
    },
    {
      "type": "connector--input",
      "accept": "connector--output",
      "acceptType": [
        "all"
      ],
      "suggestedBloqs": [
        "hwVariable",
        "selectVariable"
      ],
      "name": "47188995-8ce0-44a7-9c79-9eb90dbd093f"
    },
    {
      "type": "connector--input",
      "accept": "connector--output",
      "acceptType": [
        "all"
      ],
      "suggestedBloqs": [
        "number",
        "selectVariable"
      ],
      "name": "1b015cdd-f6df-4f47-982e-ff3f2e35847e"
    },
    {
      "type": "connector--input",
      "accept": "connector--output",
      "acceptType": [
        "all"
      ],
      "suggestedBloqs": [
        "number",
        "selectVariable"
      ],
      "name": "b816ceae-2173-4e55-be11-ee8c34616d18"
    }
  ],
  "bloqClass": "bloq-buzzer-advance",
  "content": [
    [
      {
        "alias": "text",
        "value": "bloq-buzzer-advance-sound"
      },
      {
        "bloqInputId": "BUZZER",
        "alias": "bloqInput",
        "acceptType": [
          "all"
        ],
        "suggestedBloqs": [
          "hwVariable",
          "selectVariable"
        ],
        "name": "47188995-8ce0-44a7-9c79-9eb90dbd093f"
      },
      {
        "alias": "text",
        "value": "bloq-buzzer-advance-note"
      },
      {
        "bloqInputId": "NOTE",
        "alias": "bloqInput",
        "acceptType": [
          "all"
        ],
        "suggestedBloqs": [
          "number",
          "selectVariable"
        ],
        "name": "1b015cdd-f6df-4f47-982e-ff3f2e35847e"
      },
      {
        "alias": "text",
        "value": "bloq-buzzer-advance-for"
      },
      {
        "bloqInputId": "SECONDS",
        "alias": "bloqInput",
        "acceptType": [
          "all"
        ],
        "suggestedBloqs": [
          "number",
          "selectVariable"
        ],
        "name": "b816ceae-2173-4e55-be11-ee8c34616d18"
      },
      {
        "alias": "text",
        "value": "bloq-buzzer-advance-ms"
      }
    ]
  ],
  "code": "tone({BUZZER},{NOTE},{SECONDS});\ndelay({SECONDS});",
  "arduino": {
    "code": "tone({BUZZER},{NOTE},{SECONDS});\ndelay({SECONDS});"
  },
  "python": {
    "codeLines": [
      {
        "code": "Bloque \"buzzerAdvanced\" no preparado para generar código python"
      }
    ]
  }
}