{
  "type": "statement",
  "name": "buzzerAdvanced",
  "connectors": [
    {
      "type": "connector--top",
      "accept": "connector--bottom"
    },
    {
      "type": "connector--bottom",
      "accept": "connector--top"
    },
    {
      "type": "connector--input",
      "accept": "connector--output",
      "acceptType": [
        "all"
      ],
      "suggestedBloqs": [
        "hwVariable",
        "selectVariable"
      ],
      "name": "2649cba4-bc47-46e5-8b17-6dc947abf7fb"
    },
    {
      "type": "connector--input",
      "accept": "connector--output",
      "acceptType": [
        "all"
      ],
      "suggestedBloqs": [
        "number",
        "selectVariable"
      ],
      "name": "b307a92c-dce0-432c-aa60-c5232bb2318a"
    },
    {
      "type": "connector--input",
      "accept": "connector--output",
      "acceptType": [
        "all"
      ],
      "suggestedBloqs": [
        "number",
        "selectVariable"
      ],
      "name": "4931ed04-73fd-48ad-b2af-238b5fdab2a3"
    }
  ],
  "bloqClass": "bloq-buzzer-advance",
  "content": [
    [
      {
        "alias": "text",
        "value": "bloq-buzzer-advance-sound"
      },
      {
        "bloqInputId": "BUZZER",
        "alias": "bloqInput",
        "acceptType": [
          "all"
        ],
        "suggestedBloqs": [
          "hwVariable",
          "selectVariable"
        ],
        "name": "2649cba4-bc47-46e5-8b17-6dc947abf7fb"
      },
      {
        "alias": "text",
        "value": "bloq-buzzer-advance-note"
      },
      {
        "bloqInputId": "NOTE",
        "alias": "bloqInput",
        "acceptType": [
          "all"
        ],
        "suggestedBloqs": [
          "number",
          "selectVariable"
        ],
        "name": "b307a92c-dce0-432c-aa60-c5232bb2318a"
      },
      {
        "alias": "text",
        "value": "bloq-buzzer-advance-for"
      },
      {
        "bloqInputId": "SECONDS",
        "alias": "bloqInput",
        "acceptType": [
          "all"
        ],
        "suggestedBloqs": [
          "number",
          "selectVariable"
        ],
        "name": "4931ed04-73fd-48ad-b2af-238b5fdab2a3"
      },
      {
        "alias": "text",
        "value": "bloq-buzzer-advance-ms"
      }
    ]
  ],
  "code": "tone({BUZZER},{NOTE},{SECONDS});\ndelay({SECONDS});",
  "arduino": {
    "code": "tone({BUZZER},{NOTE},{SECONDS});\ndelay({SECONDS});"
  },
  "python": {
    "codeLines": [
      {
        "code": "Bloque \"buzzerAdvanced\" no preparado para generar código python"
      }
    ]
  }
}