{
  "type": "output",
  "name": "readSensorAdvanced",
  "connectors": [
    {
      "type": "connector--output",
      "accept": "connector--input"
    },
    {
      "type": "connector--input",
      "accept": "connector--output",
      "acceptType": [
        "all"
      ],
      "name": "60ee2dcc-eda3-4598-b6cd-e71400d04273"
    }
  ],
  "bloqClass": "bloq-read-advanced",
  "content": [
    [
      {
        "alias": "text",
        "value": "bloq-read-advanced-read"
      },
      {
        "bloqInputId": "PIN",
        "alias": "bloqInput",
        "acceptType": [
          "all"
        ],
        "name": "60ee2dcc-eda3-4598-b6cd-e71400d04273"
      }
    ]
  ],
  "code": "{SENSOR.type}",
  "returnType": {
    "type": "fromDynamicDropdown",
    "idDropdown": "SENSOR",
    "options": "sensors"
  },
  "arduino": {
    "code": "¬{PIN.readSensor}"
  },
  "python": {
    "codeLines": [
      {
        "code": "Bloque \"readSensorAdvanced\" no preparado para generar código python"
      }
    ]
  }
}