{
  "type": "output",
  "name": "length",
  "connectors": [
    {
      "type": "connector--output",
      "accept": "connector--input"
    },
    {
      "type": "connector--input",
      "accept": "connector--output",
      "acceptType": [
        "String"
      ],
      "suggestedBloqs": [
        "selectVariable"
      ],
      "name": "b53d7167-7ed8-436d-872f-1fd83b84cb8f"
    }
  ],
  "bloqClass": "bloq-length",
  "content": [
    [
      {
        "alias": "text",
        "value": "bloq-length-length"
      },
      {
        "bloqInputId": "TEXT",
        "alias": "bloqInput",
        "acceptType": [
          "String"
        ],
        "suggestedBloqs": [
          "selectVariable"
        ],
        "name": "b53d7167-7ed8-436d-872f-1fd83b84cb8f"
      }
    ]
  ],
  "code": "{TEXT}.length()",
  "returnType": {
    "type": "simple",
    "value": "float"
  },
  "arduino": {
    "code": "{TEXT}.length()"
  },
  "python": {
    "codeLines": [
      {
        "code": "Bloque \"length\" no preparado para generar código python"
      }
    ]
  }
}