{
  "type": "output",
  "name": "stringSum",
  "connectors": [
    {
      "type": "connector--output",
      "accept": "connector--input"
    },
    {
      "type": "connector--input",
      "accept": "connector--output",
      "acceptType": [
        "String"
      ],
      "suggestedBloqs": [
        "string",
        "selectVariable"
      ],
      "name": "589638f0-33ca-4c73-b6d8-28996224a617"
    },
    {
      "type": "connector--input",
      "accept": "connector--output",
      "acceptType": [
        "String"
      ],
      "suggestedBloqs": [
        "string",
        "selectVariable"
      ],
      "name": "6e562779-3f0d-4cc7-b304-712a26f5f639"
    }
  ],
  "bloqClass": "bloq-string-sum",
  "content": [
    [
      {
        "bloqInputId": "ARG1",
        "alias": "bloqInput",
        "acceptType": [
          "String"
        ],
        "suggestedBloqs": [
          "string",
          "selectVariable"
        ],
        "name": "589638f0-33ca-4c73-b6d8-28996224a617"
      },
      {
        "alias": "text",
        "value": "+"
      },
      {
        "bloqInputId": "ARG2",
        "alias": "bloqInput",
        "acceptType": [
          "String"
        ],
        "suggestedBloqs": [
          "string",
          "selectVariable"
        ],
        "name": "6e562779-3f0d-4cc7-b304-712a26f5f639"
      }
    ]
  ],
  "code": "String({ARG1})+String({ARG2})",
  "returnType": {
    "type": "simple",
    "value": "String"
  },
  "arduino": {
    "code": "String({ARG1})+String({ARG2})"
  },
  "python": {
    "codeLines": [
      {
        "code": "Bloque \"stringSum\" no preparado para generar código python"
      }
    ]
  }
}